README.md
setup.cfg
setup.py
reluctant_walks/__init__.py
reluctant_walks/config.py
reluctant_walks/graphics.py
reluctant_walks/plane.py
reluctant_walks/reference.py
reluctant_walks.egg-info/PKG-INFO
reluctant_walks.egg-info/SOURCES.txt
reluctant_walks.egg-info/dependency_links.txt
reluctant_walks.egg-info/top_level.txt
reluctant_walks/compilers/__init__.py
reluctant_walks/compilers/boltzoc.py
reluctant_walks/compilers/combstruct.py
reluctant_walks/compilers/genrgens.py
reluctant_walks/compilers/maple.py