Metadata-Version: 1.1
Name: reluctant-walks
Version: 1.2
Summary: Python/Sage package to study and sample reluctant random walks in the positive quadrant.
Home-page: https://github.com/jlumbroso/reluctant-walks
Author: Jérémie Lumbroso
Author-email: lumbroso@cs.princeton.edu
License: LGPLv3
Keywords: combinatorics,random walks,sampling
Platform: UNKNOWN
Classifier: Programming Language :: Python :: 2
Classifier: Programming Language :: Python :: 2.7
Classifier: Programming Language :: Python :: 3
Classifier: Programming Language :: Python :: 3.4
Classifier: Programming Language :: Python :: 3.5
Classifier: Topic :: Scientific/Engineering :: Mathematics
Classifier: Topic :: Software Development :: Libraries :: Python Modules
Classifier: Intended Audience :: Developers
Classifier: Intended Audience :: Education
Classifier: Intended Audience :: Science/Research
Classifier: Operating System :: OS Independent
Classifier: License :: OSI Approved :: GNU Lesser General Public License v3 (LGPLv3)
Classifier: Development Status :: 5 - Production/Stable
